quimerax/__init__.py
quimerax/client.py
quimerax/enums.py
quimerax-0.1.2.dist-info/licenses/LICENSE
quimerax-0.1.2.dist-info/METADATA
quimerax-0.1.2.dist-info/WHEEL
quimerax-0.1.2.dist-info/top_level.txt
quimerax-0.1.2.dist-info/RECORD
